think_mcp_client/__init__.py
think_mcp_client/cli.py
think_mcp_client/client.py
think_mcp_client/manager.py
think_mcp_client/mcp_processor.py
think_mcp_client/utils/__init__.py
think_mcp_client/utils/command.py
think_mcp_client-0.2.5.dist-info/METADATA
think_mcp_client-0.2.5.dist-info/WHEEL
think_mcp_client-0.2.5.dist-info/RECORD
