Metadata-Version: 2.4
Name: think-mcp-client
Version: 0.2.5
Summary: MCP (Model Control Protocol) 客户端，用于与 MCP 服务器交互
Author-email: Think Team <yezhenjie@outlook.de>
License: MIT
Requires-Python: >=3.12
Requires-Dist: mcp>=1.3.0
Requires-Dist: prompt-toolkit>=3.0.0
Requires-Dist: pydantic>=2.0.0
Requires-Dist: pyyaml>=6.0.2
Requires-Dist: rich>=10.0.0
Requires-Dist: think-llm-client>=0.4.0
Requires-Dist: typing-extensions>=4.0.0
Provides-Extra: dev
Requires-Dist: black>=23.0.0; extra == 'dev'
Requires-Dist: flake8>=6.0.0; extra == 'dev'
Requires-Dist: isort>=5.0.0; extra == 'dev'
Requires-Dist: mypy>=1.0.0; extra == 'dev'
Requires-Dist: pytest-asyncio>=0.21.0; extra == 'dev'
Requires-Dist: pytest>=7.0.0; extra == 'dev'
